nameko_stripe/__init__.py
nameko_stripe/stripe_dep.py
nameko_stripe/tests/__init__.py
nameko_stripe/tests/test_nameko_stripe.py
nameko_stripe-0.1.3.dist-info/METADATA
nameko_stripe-0.1.3.dist-info/RECORD
nameko_stripe-0.1.3.dist-info/WHEEL
nameko_stripe-0.1.3.dist-info/top_level.txt
